custom_forms_cli/__init__.py
custom_forms_cli/automate.py
custom_forms_cli/cli.py
custom_forms_cli/get.py
custom_forms_cli/get_backup.py
custom_forms_cli/password_input.py
custom_forms_cli/put.py
custom_forms_cli-0.1.0.dist-info/METADATA
custom_forms_cli-0.1.0.dist-info/WHEEL
custom_forms_cli-0.1.0.dist-info/entry_points.txt
custom_forms_cli-0.1.0.dist-info/top_level.txt
custom_forms_cli-0.1.0.dist-info/RECORD
