Metadata-Version: 2.4
Name: custom_forms_cli
Version: 0.1.0
Summary: A CLI toolkit for managing XNAT custom forms (get, put, automate).
Author-email: Rahul Rajput <rahul.rajput@proxmed.com>
License-Expression: MIT
Classifier: Development Status :: 4 - Beta
Classifier: Intended Audience :: Developers
Classifier: Programming Language :: Python :: 3
Classifier: Programming Language :: Python :: 3.8
Classifier: Programming Language :: Python :: 3.9
Classifier: Programming Language :: Python :: 3.10
Classifier: Programming Language :: Python :: 3.11
Requires-Python: >=3.8
Requires-Dist: pandas
Requires-Dist: pytz
Requires-Dist: requests
Requires-Dist: typer
Requires-Dist: pyxnat
Requires-Dist: typing-extensions
Requires-Dist: xnat
Requires-Dist: openpyxl
